newtonpy/__init__.py
newtonpy-0.1.0.dist-info/LICENSE
newtonpy-0.1.0.dist-info/WHEEL
newtonpy-0.1.0.dist-info/METADATA
newtonpy-0.1.0.dist-info/RECORD
