Metadata-Version: 2.1
Name: newtonpy
Version: 0.1.0
Summary: A package to solve nonlinear equations
Home-page: https://github.com/felipemarkson/newtonpy
License: MIT
Author: Felipe M. S. Monteiro
Author-email: fmarkson@outlook.com
Requires-Python: >=3.8,<4.0
Classifier: Development Status :: 4 - Beta
Classifier: Intended Audience :: Science/Research
Classifier: License :: OSI Approved :: MIT License
Classifier: Programming Language :: Python :: 3
Classifier: Programming Language :: Python :: 3.8
Classifier: Topic :: Software Development :: Libraries :: Python Modules
Requires-Dist: numpy (>=1.19.0,<2.0.0)
Project-URL: Documentation, https://github.com/felipemarkson/newtonpy
Project-URL: Repository, https://github.com/felipemarkson/newtonpy
